excalibrate/__init__.py
excalibrate/test.py
excalibrate-0.0.6.dist-info/LICENSE
excalibrate-0.0.6.dist-info/METADATA
excalibrate-0.0.6.dist-info/WHEEL
excalibrate-0.0.6.dist-info/top_level.txt
excalibrate-0.0.6.dist-info/RECORD
