Metadata-Version: 2.1
Name: excalibrate
Version: 0.0.6
Summary: Extended Bayesian algorithm for radiometer calibration
Author-email: Ian Roque <laurent.roque@yahoo.com>
Project-URL: Homepage, https://github.com/laurentroque/Excalibrate
Classifier: Programming Language :: Python :: 3
Classifier: Operating System :: OS Independent
Requires-Python: >=3.7
License-File: LICENSE
